touying/__init__.py
touying/cli.py
touying/exporter.py
touying/template.html.j2
touying-0.14.4.dist-info/licenses/LICENSE
touying-0.14.4.dist-info/METADATA
touying-0.14.4.dist-info/WHEEL
touying-0.14.4.dist-info/entry_points.txt
touying-0.14.4.dist-info/top_level.txt
touying-0.14.4.dist-info/RECORD
