Metadata-Version: 2.4
Name: touying
Version: 0.14.4
Summary: Export presentation slides in various formats for Touying
Author-email: OrangeX4 <318483724@qq.com>
License: MIT
Project-URL: Home, https://github.com/touying-typ/touying-exporter
Keywords: presentation,slides,export
Classifier: Development Status :: 4 - Beta
Classifier: Intended Audience :: Developers
Classifier: License :: OSI Approved :: MIT License
License-File: LICENSE
Requires-Dist: typst>=0.14.4
Requires-Dist: python-pptx>=0.6
Requires-Dist: pillow
Requires-Dist: jinja2
Dynamic: license-file
